isPowerOf2/__init__.py
isPowerOf2-1.0.1.dist-info/METADATA
isPowerOf2-1.0.1.dist-info/WHEEL
isPowerOf2-1.0.1.dist-info/top_level.txt
isPowerOf2-1.0.1.dist-info/RECORD
